agentflowpy/__init__.py
agentflowpy/agent.py
agentflowpy/context.py
agentflowpy-1.0.0.dist-info/licenses/LICENSE.md
agentflowpy-1.0.0.dist-info/METADATA
agentflowpy-1.0.0.dist-info/WHEEL
agentflowpy-1.0.0.dist-info/top_level.txt
agentflowpy-1.0.0.dist-info/RECORD
