Metadata-Version: 2.4
Name: agentflowpy
Version: 1.0.0
Summary: Practial module to build AI agents with context management and step-based execution.
Author-email: Ozel Umut Tam <ozel.umut.tam@gmail.com>
License: NonCommercial No-AI License
Requires-Python: >=3.12
License-File: LICENSE.md
Requires-Dist: pydantic>=2.11.0
Requires-Dist: typing-extensions>=4.0.0
Provides-Extra: dev
Requires-Dist: pytest>=8.0.0; extra == "dev"
Requires-Dist: pytest-asyncio>=1.0.0; extra == "dev"
Dynamic: license-file
